{
  "annotations": {
    "list": []
  },
  "editable": true,
  "fiscalYearStartMonth": 0,
  "graphTooltip": 1,
  "id": null,
  "links": [],
  "panels": [
    {
      "datasource": {
        "type": "prometheus",
        "uid": "prometheus"
      },
      "fieldConfig": {
        "defaults": {
          "color": {
            "mode": "thresholds"
          },
          "mappings": [],
          "thresholds": {
            "mode": "absolute",
            "steps": [
              { "color": "green", "value": null },
              { "color": "yellow", "value": 10 },
              { "color": "red", "value": 50 }
            ]
          },
          "unit": "currencyUSD"
        },
        "overrides": []
      },
      "gridPos": { "h": 8, "w": 6, "x": 0, "y": 0 },
      "id": 1,
      "options": {
        "colorMode": "value",
        "graphMode": "area",
        "justifyMode": "auto",
        "orientation": "auto",
        "percentChangeColorMode": "standard",
        "reduceOptions": {
          "calcs": ["lastNotNull"],
          "fields": "",
          "values": false
        },
        "showPercentChange": false,
        "textMode": "auto",
        "wideLayout": true
      },
      "pluginVersion": "11.6.0",
      "targets": [
        {
          "datasource": {
            "type": "prometheus",
            "uid": "prometheus"
          },
          "expr": "sum(cost_usd_total)",
          "legendFormat": "Total Cost",
          "refId": "A"
        }
      ],
      "title": "Total Cost",
      "type": "stat"
    },
    {
      "datasource": {
        "type": "prometheus",
        "uid": "prometheus"
      },
      "fieldConfig": {
        "defaults": {
          "color": {
            "mode": "thresholds"
          },
          "mappings": [],
          "thresholds": {
            "mode": "absolute",
            "steps": [
              { "color": "green", "value": null },
              { "color": "yellow", "value": 0.5 },
              { "color": "red", "value": 2 }
            ]
          },
          "unit": "currencyUSD"
        },
        "overrides": []
      },
      "gridPos": { "h": 8, "w": 4, "x": 6, "y": 0 },
      "id": 2,
      "options": {
        "colorMode": "value",
        "graphMode": "none",
        "justifyMode": "auto",
        "orientation": "auto",
        "percentChangeColorMode": "standard",
        "reduceOptions": {
          "calcs": ["mean"],
          "fields": "",
          "values": false
        },
        "showPercentChange": false,
        "textMode": "auto",
        "wideLayout": true
      },
      "pluginVersion": "11.6.0",
      "targets": [
        {
          "datasource": {
            "type": "prometheus",
            "uid": "prometheus"
          },
          "expr": "sum(cost_usd_total) / clamp_min(count(requirements_by_status), 1)",
          "legendFormat": "Cost/Req",
          "refId": "A"
        }
      ],
      "title": "Cost Per Requirement",
      "type": "stat"
    },
    {
      "datasource": {
        "type": "prometheus",
        "uid": "prometheus"
      },
      "fieldConfig": {
        "defaults": {
          "color": {
            "mode": "palette-classic"
          },
          "mappings": [],
          "unit": "currencyUSD"
        },
        "overrides": []
      },
      "gridPos": { "h": 8, "w": 14, "x": 10, "y": 0 },
      "id": 3,
      "options": {
        "displayMode": "gradient",
        "maxVizHeight": 300,
        "minVizHeight": 16,
        "minVizWidth": 8,
        "namePlacement": "auto",
        "orientation": "horizontal",
        "reduceOptions": {
          "calcs": ["lastNotNull"],
          "fields": "",
          "values": false
        },
        "showUnfilled": true,
        "sizing": "auto",
        "valueMode": "color"
      },
      "pluginVersion": "11.6.0",
      "targets": [
        {
          "datasource": {
            "type": "prometheus",
            "uid": "prometheus"
          },
          "expr": "cost_usd_total",
          "legendFormat": "{{agent_id}}",
          "refId": "A"
        }
      ],
      "title": "Cost By Agent",
      "type": "barchart"
    },
    {
      "datasource": {
        "type": "prometheus",
        "uid": "prometheus"
      },
      "fieldConfig": {
        "defaults": {
          "color": {
            "mode": "palette-classic"
          },
          "mappings": [],
          "unit": "currencyUSD"
        },
        "overrides": []
      },
      "gridPos": { "h": 10, "w": 12, "x": 0, "y": 8 },
      "id": 4,
      "options": {
        "legend": {
          "calcs": ["sum", "max"],
          "displayMode": "table",
          "placement": "bottom",
          "showLegend": true
        },
        "tooltip": {
          "mode": "multi",
          "sort": "desc"
        }
      },
      "pluginVersion": "11.6.0",
      "targets": [
        {
          "datasource": {
            "type": "prometheus",
            "uid": "prometheus"
          },
          "expr": "sum(rate(cost_usd_total[5m])) by (agent_id)",
          "legendFormat": "{{agent_id}}",
          "refId": "A"
        }
      ],
      "title": "Cost Over Time",
      "type": "timeseries"
    },
    {
      "datasource": {
        "type": "prometheus",
        "uid": "prometheus"
      },
      "fieldConfig": {
        "defaults": {
          "color": {
            "mode": "palette-classic"
          },
          "mappings": [],
          "unit": "currencyUSD"
        },
        "overrides": []
      },
      "gridPos": { "h": 10, "w": 12, "x": 12, "y": 8 },
      "id": 5,
      "options": {
        "legend": {
          "calcs": ["sum"],
          "displayMode": "table",
          "placement": "bottom",
          "showLegend": true
        },
        "tooltip": {
          "mode": "multi",
          "sort": "desc"
        }
      },
      "pluginVersion": "11.6.0",
      "targets": [
        {
          "datasource": {
            "type": "prometheus",
            "uid": "prometheus"
          },
          "expr": "sum(increase(cost_usd_total[1d]))",
          "legendFormat": "Daily Cost",
          "refId": "A"
        }
      ],
      "title": "Daily Cost Trend",
      "type": "timeseries"
    },
    {
      "datasource": {
        "type": "prometheus",
        "uid": "prometheus"
      },
      "fieldConfig": {
        "defaults": {
          "color": {
            "mode": "thresholds"
          },
          "mappings": [],
          "thresholds": {
            "mode": "absolute",
            "steps": [
              { "color": "green", "value": null },
              { "color": "red", "value": 5 }
            ]
          },
          "unit": "currencyUSD"
        },
        "overrides": [
          {
            "matcher": {
              "id": "byName",
              "options": "Session"
            },
            "properties": [
              {
                "id": "custom.width",
                "value": 300
              }
            ]
          }
        ]
      },
      "gridPos": { "h": 10, "w": 24, "x": 0, "y": 18 },
      "id": 6,
      "options": {
        "footer": {
          "countRows": false,
          "enablePagination": false,
          "fields": "",
          "reducer": ["sum"],
          "show": false
        },
        "showHeader": true,
        "sortBy": [
          {
            "desc": true,
            "displayName": "Value"
          }
        ]
      },
      "pluginVersion": "11.6.0",
      "targets": [
        {
          "datasource": {
            "type": "prometheus",
            "uid": "prometheus"
          },
          "expr": "topk(5, cost_usd_total)",
          "format": "table",
          "instant": true,
          "legendFormat": "{{agent_id}}",
          "refId": "A"
        }
      ],
      "title": "Top 5 Most Expensive Sessions",
      "type": "table"
    }
  ],
  "refresh": "30s",
  "schemaVersion": 39,
  "tags": ["ai-native", "cost"],
  "templating": {
    "list": []
  },
  "time": {
    "from": "now-24h",
    "to": "now"
  },
  "timepicker": {},
  "timezone": "browser",
  "title": "Token Cost Dashboard",
  "uid": "cost-dashboard",
  "version": 1,
  "weekStart": ""
}
